mynotes/__init__.py
mynotes/cli.py
mynotes/config.py
mynotes/constants.py
mynotes/gen.py
mynotes/plugins_html.py
mynotes/utils.py
tests/__init__.py
tests/test_config.py
tests/test_gen.py
tests/test_plugins_html.py
tests/test_utils.py
tests/tree.py
mynotes-1.0.1.dist-info/LICENSE
mynotes-1.0.1.dist-info/METADATA
mynotes-1.0.1.dist-info/WHEEL
mynotes-1.0.1.dist-info/entry_points.txt
mynotes-1.0.1.dist-info/top_level.txt
mynotes-1.0.1.dist-info/RECORD
