Metadata-Version: 2.1
Name: mynotes
Version: 1.0.1
Summary: Build index and generate HTML for markdown notes
Home-page: https://gitlab.com/yorickbrunet/mynotes
Author: Yorick Brunet
Author-email: mynotes@yok.ch
License: GPL version 3 or later
Platform: UNKNOWN
Classifier: Development Status :: 5 - Production/Stable
Classifier: Environment :: Console
Classifier: Programming Language :: Python :: 3
Classifier: Programming Language :: Python :: 3.7
Classifier: Topic :: Utilities
Classifier: License :: OSI Approved :: GNU General Public License v3 or later (GPLv3+)
Requires-Python: >= 3.7
Requires-Dist: py-gfm
Requires-Dist: Pygments
